amaraapi/__init__.py
amaraapi/amara.py
amaraapi/amara_tools.py
amaraapi/amara_video.py
amaraapi/exceptions.py
amaraapi-0.0.5.dist-info/METADATA
amaraapi-0.0.5.dist-info/WHEEL
amaraapi-0.0.5.dist-info/top_level.txt
amaraapi-0.0.5.dist-info/RECORD
